setup.cfg
setup.py
millpy/__init__.py
millpy/exceptions.py
millpy/test.py
millpy.egg-info/PKG-INFO
millpy.egg-info/SOURCES.txt
millpy.egg-info/dependency_links.txt
millpy.egg-info/requires.txt
millpy.egg-info/top_level.txt
millpy.egg-info/zip-safe