Metadata-Version: 1.0
Name: millpy
Version: 1.0.5
Summary: Paymill for Python.
Home-page: http://bruun.co/
Author: Nick Bruun
Author-email: nick@bruun.co
License: UNKNOWN
Platform: UNKNOWN
